cli.py
tf_cloud_cli/__init__.py
tf_cloud_cli/api.py
tf_cloud_cli/token.py
tf_cloud_cli-0.0.2.dist-info/LICENSE
tf_cloud_cli-0.0.2.dist-info/METADATA
tf_cloud_cli-0.0.2.dist-info/WHEEL
tf_cloud_cli-0.0.2.dist-info/entry_points.txt
tf_cloud_cli-0.0.2.dist-info/top_level.txt
tf_cloud_cli-0.0.2.dist-info/RECORD
