Metadata-Version: 2.1
Name: tf-cloud-cli
Version: 0.0.2
Summary: A CLI to the Terraform Cloud API
Home-page: https://github.com/njeirath/tf_cloud_cli
Author: njeirath
License: UNKNOWN
Platform: UNKNOWN
Classifier: Programming Language :: Python :: 3
Classifier: License :: OSI Approved :: MIT License
Classifier: Operating System :: OS Independent
Requires-Dist: click (==7.1.1)
Requires-Dist: requests (==2.23.0)
